README.md
argtools.py
setup.py
argtools.egg-info/PKG-INFO
argtools.egg-info/SOURCES.txt
argtools.egg-info/dependency_links.txt
argtools.egg-info/top_level.txt