Metadata-Version: 1.1
Name: argtools
Version: 0.1.2
Summary: A wrapper of argparse that helps to build command line tools with minimal effort.
Home-page: https://github.com/m1m0r1/argtools.py
Author: Takahiro Mimori
Author-email: takahiro.mimori@gmail.com
License: UNKNOWN
Keywords: argparse subcommand command cli
Platform: UNKNOWN
Classifier: Programming Language :: Python
Classifier: Topic :: Software Development :: Libraries :: Python Modules
